causalAssembly/__init__.py
causalAssembly/dag.py
causalAssembly/dag_utils.py
causalAssembly/drf_fitting.py
causalAssembly/metrics.py
causalAssembly/models_dag.py
causalAssembly/models_fcm.py
causalAssembly/pdag.py
causalassembly-1.2.1.dist-info/licenses/LICENSE.txt
causalassembly-1.2.1.dist-info/METADATA
causalassembly-1.2.1.dist-info/WHEEL
causalassembly-1.2.1.dist-info/top_level.txt
causalassembly-1.2.1.dist-info/RECORD
