Metadata-Version: 2.4
Name: causalAssembly
Version: 1.2.1
Summary: Generating production line data with available causal ground truth
Author-email: Konstantin Göbler <konstantin.goebler@de.bosch.com>
Project-URL: Homepage, https://github.com/boschresearch/causalAssembly
Project-URL: Documentation, https://boschresearch.github.io/causalAssembly/
Project-URL: Repository, https://github.com/boschresearch/causalAssembly
Project-URL: Issues, https://github.com/boschresearch/causalAssembly/issues
Project-URL: Changelog, https://github.com/boschresearch/causalAssembly/blob/main/CHANGELOG.md
Requires-Python: >3.10.0
License-File: LICENSE.txt
Requires-Dist: sympy
Requires-Dist: networkx
Requires-Dist: scipy
Requires-Dist: numpy
Requires-Dist: pandas
Requires-Dist: matplotlib
Requires-Dist: rpy2
Requires-Dist: requests
Provides-Extra: dev
Requires-Dist: mike; extra == "dev"
Requires-Dist: mkdocs; extra == "dev"
Requires-Dist: mkdocs-material; extra == "dev"
Requires-Dist: mkdocstrings[python]; extra == "dev"
Requires-Dist: pip-licenses; extra == "dev"
Requires-Dist: pip-tools; extra == "dev"
Requires-Dist: pre-commit; extra == "dev"
Requires-Dist: pytest; extra == "dev"
Requires-Dist: pytest-cov; extra == "dev"
Requires-Dist: ruff; extra == "dev"
Requires-Dist: uv; extra == "dev"
Dynamic: license-file
